[{
  "src": "http://sc1.111ttt.cn:8282/2016/1/07m/07/200072241569.m4a?tflag=1513940398&pin=4bfdb9fa974b8b03724686c44831c52d#.mp3",
  "title": "China-X",
  "author": "徐梦圆",
  "pic": "http://p1.music.126.net/hH4UmteuzsqZHacrr3YS_g==/18358545649308968.jpg"
}, {
  "src": "http://sc1.111ttt.cn:8282/2016/1/07m/06/200061120016.m4a?tflag=1513940398&pin=4bfdb9fa974b8b03724686c44831c52d#.mp3",
  "title": "China-P",
  "author": "徐梦圆",
  "pic": "http://p1.music.126.net/QXy6gWjZnsjEb9t-wfCX7w==/16600426556676613.jpg"
}, {
  "src": "http://sc1.111ttt.cn:8282/2015/1/09m/19/102191059559.m4a?tflag=1513940398&pin=4bfdb9fa974b8b03724686c44831c52d#.mp3",
  "title": "Life",
  "author": "Tobu",
  "pic": "http://p1.music.126.net/ol5I7So8kHncjiFWLLYb8Q==/2262794929978909.jpg"
}, {
  "src": "http://sc1.111ttt.cn:8282/2015/1/11m/01/104010652059.m4a?tflag=1513940398&pin=4bfdb9fa974b8b03724686c44831c52d#.mp3",
  "title": "Mesmerize",
  "author": "Tobu",
  "pic": "http://p1.music.126.net/w97MGGZztY9opkoLxmT5QQ==/6641050232329451.jpg"
}, {
  "src": "http://sc1.111ttt.cn:8282/2015/1/06m/06/99060941326.m4a?tflag=1513940398&pin=4bfdb9fa974b8b03724686c44831c52d#.mp3",
  "title": "演员",
  "author": "薛之谦",
  "pic": "http://p1.music.126.net/IeNepGO_b0uKEzF3ASYA5w==/5715261441302954.jpg"
}, {
  "src": "http://sc1.111ttt.cn:8282/2014/1/09m/28/2281716032.m4a?tflag=1513940398&pin=4bfdb9fa974b8b03724686c44831c52d#.mp3",
  "title": "刘哈哈与大先生",
  "author": "刘心",
  "pic": "http://p1.music.126.net/HfQfxH3jfCUCDhhT_QZLYg==/109951163042634034.jpg"
}]